{"assets/audio/background.mp3":["assets/audio/background.mp3"],"assets/audio/typewriter_key.mp3":["assets/audio/typewriter_key.mp3"],"assets/fonts/Orbitron-Bold.ttf":["assets/fonts/Orbitron-Bold.ttf"],"assets/fonts/Orbitron-Regular.ttf":["assets/fonts/Orbitron-Regular.ttf"],"assets/gif/background.gif":["assets/gif/background.gif"],"assets/icons/en_flag.png":["assets/icons/en_flag.png"],"assets/icons/tr_flag.png":["assets/icons/tr_flag.png"],"assets/images/11.png":["assets/images/11.png"],"assets/images/background_static.jpg":["assets/images/background_static.jpg"],"assets/images/buzul1.png":["assets/images/buzul1.png"],"assets/images/triverse_box.jpg":["assets/images/triverse_box.jpg"],"assets/images/triverse_gameplay.jpg":["assets/images/triverse_gameplay.jpg"],"assets/images/uzaybolum1.jpg":["assets/images/uzaybolum1.jpg"]}